examples/__init__.py
examples/get_furigana_html_example.py
pyrigana/__init__.py
pyrigana/pyrigana.py
pyrigana/_internal/__init__.py
pyrigana/_internal/utils.py
pyrigana/tests/__init__.py
pyrigana/tests/test_compare_list.py
pyrigana/tests/test_furigana_html.py
pyrigana/tests/test_pair_list.py
pyrigana-0.1.1.dist-info/METADATA
pyrigana-0.1.1.dist-info/WHEEL
pyrigana-0.1.1.dist-info/top_level.txt
pyrigana-0.1.1.dist-info/RECORD
