Metadata-Version: 2.1
Name: pyrigana
Version: 0.1.1
Summary: A brief description of my package
Home-page: https://github.com/aknay/pyrigana
Author: Nay Aung Kyaw
Author-email: aknay@outlook.com
License: MIT
Classifier: Programming Language :: Python :: 3
Classifier: License :: OSI Approved :: MIT License
Classifier: Operating System :: OS Independent
Requires-Python: >=3.6
Requires-Dist: jaconv
Requires-Dist: fugashi
Requires-Dist: fugashi[unidic-lite]
Provides-Extra: dev
Requires-Dist: pytest ; extra == 'dev'
